AUTHORS
ChangeLog
LICENSE
MANIFEST.in
README.md
setup.cfg
setup.py
docs/Makefile
docs/conf.py
docs/index.rst
docs/module_guide.rst
test/__init__.py
test/helper.py
test/parameters.json
test/test_InfoExtractor.py
test/test_YoutubeDL.py
test/test_YoutubeDLCookieJar.py
test/test_aes.py
test/test_age_restriction.py
test/test_all_urls.py
test/test_cache.py
test/test_compat.py
test/test_download.py
test/test_downloader_http.py
test/test_execution.py
test/test_http.py
test/test_iqiyi_sdk_interpreter.py
test/test_jsinterp.py
test/test_netrc.py
test/test_options.py
test/test_postprocessors.py
test/test_socks.py
test/test_subtitles.py
test/test_swfinterp.py
test/test_unicode_literals.py
test/test_update.py
test/test_utils.py
test/test_verbose_output.py
test/test_write_annotations.py
test/test_youtube_lists.py
test/test_youtube_misc.py
test/test_youtube_signature.py
test/testcert.pem
test/versions.json
test/swftests/.gitignore
test/swftests/ArrayAccess.as
test/swftests/ClassCall.as
test/swftests/ClassConstruction.as
test/swftests/ConstArrayAccess.as
test/swftests/ConstantInt.as
test/swftests/DictCall.as
test/swftests/EqualsOperator.as
test/swftests/LocalVars.as
test/swftests/MemberAssignment.as
test/swftests/NeOperator.as
test/swftests/PrivateCall.as
test/swftests/PrivateVoidCall.as
test/swftests/StaticAssignment.as
test/swftests/StaticRetrieval.as
test/swftests/StringBasics.as
test/swftests/StringCharCodeAt.as
test/swftests/StringConversion.as
test/testdata/cookies/httponly_cookies.txt
test/testdata/cookies/malformed_cookies.txt
test/testdata/cookies/session_cookies.txt
test/testdata/f4m/custom_base_url.f4m
test/testdata/m3u8/pluzz_francetv_11507.m3u8
test/testdata/m3u8/teamcoco_11995.m3u8
test/testdata/m3u8/ted_18923.m3u8
test/testdata/m3u8/toggle_mobile_12211.m3u8
test/testdata/m3u8/twitch_vod.m3u8
test/testdata/m3u8/vidio.m3u8
test/testdata/mpd/float_duration.mpd
test/testdata/mpd/unfragmented.mpd
test/testdata/mpd/urls_only.mpd
test/testdata/xspf/foo_xspf.xspf
youtube_dl_fork.egg-info/PKG-INFO
youtube_dl_fork.egg-info/SOURCES.txt
youtube_dl_fork.egg-info/dependency_links.txt
youtube_dl_fork.egg-info/entry_points.txt
youtube_dl_fork.egg-info/top_level.txt