Metadata-Version: 1.2
Name: youtube-dl-fork
Version: 2022.6.29
Summary: YouTube video downloader
Home-page: https://github.com/ytdl-org/youtube-dl
Author: Ricardo Garcia
Author-email: ytdl@yt-dl.org
Maintainer: Sergey M.
Maintainer-email: dstftw@gmail.com
License: Unlicense
Platform: UNKNOWN
Classifier: Topic :: Multimedia :: Video
Classifier: Development Status :: 5 - Production/Stable
Classifier: Environment :: Console
Classifier: License :: Public Domain
Classifier: Programming Language :: Python
Classifier: Programming Language :: Python :: 2
Classifier: Programming Language :: Python :: 2.6
Classifier: Programming Language :: Python :: 2.7
Classifier: Programming Language :: Python :: 3
Classifier: Programming Language :: Python :: 3.2
Classifier: Programming Language :: Python :: 3.3
Classifier: Programming Language :: Python :: 3.4
Classifier: Programming Language :: Python :: 3.5
Classifier: Programming Language :: Python :: 3.6
Classifier: Programming Language :: Python :: 3.7
Classifier: Programming Language :: Python :: 3.8
Classifier: Programming Language :: Python :: Implementation
Classifier: Programming Language :: Python :: Implementation :: CPython
Classifier: Programming Language :: Python :: Implementation :: IronPython
Classifier: Programming Language :: Python :: Implementation :: Jython
Classifier: Programming Language :: Python :: Implementation :: PyPy
